CHANGES.txt
LICENSE.txt
MANIFEST.in
README.txt
TODO.txt
buildout.cfg
setup.py
eggs/BTrees-6.1-py3.10-win-amd64.egg/EGG-INFO/LICENSE.txt
eggs/BTrees-6.1-py3.10-win-amd64.egg/EGG-INFO/requires.txt
eggs/BTrees-6.1-py3.10-win-amd64.egg/EGG-INFO/top_level.txt
eggs/WSGIProxy2-0.5.1-py3.10.egg/EGG-INFO/entry_points.txt
eggs/WSGIProxy2-0.5.1-py3.10.egg/EGG-INFO/requires.txt
eggs/WSGIProxy2-0.5.1-py3.10.egg/EGG-INFO/top_level.txt
eggs/WebOb-1.8.7-py3.10.egg/EGG-INFO/license.txt
eggs/WebOb-1.8.7-py3.10.egg/EGG-INFO/requires.txt
eggs/WebOb-1.8.7-py3.10.egg/EGG-INFO/top_level.txt
eggs/WebTest-2.0.35-py3.10.egg/EGG-INFO/entry_points.txt
eggs/WebTest-2.0.35-py3.10.egg/EGG-INFO/requires.txt
eggs/WebTest-2.0.35-py3.10.egg/EGG-INFO/top_level.txt
eggs/ZConfig-4.2-py3.10.egg/EGG-INFO/LICENSE.txt
eggs/ZConfig-4.2-py3.10.egg/EGG-INFO/entry_points.txt
eggs/ZConfig-4.2-py3.10.egg/EGG-INFO/requires.txt
eggs/ZConfig-4.2-py3.10.egg/EGG-INFO/top_level.txt
eggs/ZConfig-4.2-py3.10.egg/ZConfig/schemaless.txt
eggs/ZConfig-4.2-py3.10.egg/ZConfig/tests/input/non-ascii.txt
eggs/ZConfig-4.2-py3.10.egg/ZConfig/tests/library/README.txt
eggs/ZConfig-4.2-py3.10.egg/ZConfig/tests/zipsource/README.txt
eggs/beautifulsoup4-4.6.1-py3.10.egg/EGG-INFO/requires.txt
eggs/beautifulsoup4-4.6.1-py3.10.egg/EGG-INFO/top_level.txt
eggs/cffi-1.17.1-py3.10-win-amd64.egg/EGG-INFO/entry_points.txt
eggs/cffi-1.17.1-py3.10-win-amd64.egg/EGG-INFO/requires.txt
eggs/cffi-1.17.1-py3.10-win-amd64.egg/EGG-INFO/top_level.txt
eggs/coverage-7.10.4-py3.10.egg/EGG-INFO/entry_points.txt
eggs/coverage-7.10.4-py3.10.egg/EGG-INFO/requires.txt
eggs/coverage-7.10.4-py3.10.egg/EGG-INFO/top_level.txt
eggs/coverage-7.10.4-py3.10.egg/EGG-INFO/licenses/LICENSE.txt
eggs/coverage-7.10.5-py3.10-win-amd64.egg/EGG-INFO/entry_points.txt
eggs/coverage-7.10.5-py3.10-win-amd64.egg/EGG-INFO/requires.txt
eggs/coverage-7.10.5-py3.10-win-amd64.egg/EGG-INFO/top_level.txt
eggs/coverage-7.10.5-py3.10-win-amd64.egg/EGG-INFO/licenses/LICENSE.txt
eggs/future-1.0.0-py3.10.egg/EGG-INFO/LICENSE.txt
eggs/future-1.0.0-py3.10.egg/EGG-INFO/entry_points.txt
eggs/future-1.0.0-py3.10.egg/EGG-INFO/top_level.txt
eggs/lxml-4.9.4-py3.10-win-amd64.egg/EGG-INFO/LICENSE.txt
eggs/lxml-4.9.4-py3.10-win-amd64.egg/EGG-INFO/LICENSES.txt
eggs/lxml-4.9.4-py3.10-win-amd64.egg/EGG-INFO/requires.txt
eggs/lxml-4.9.4-py3.10-win-amd64.egg/EGG-INFO/top_level.txt
eggs/lxml-4.9.4-py3.10-win-amd64.egg/lxml/isoschematron/resources/xsl/iso-schematron-xslt1/readme.txt
eggs/multipart-1.3.0-py3.10.egg/EGG-INFO/requires.txt
eggs/p01.cgi-0.6.1-py3.10.egg/EGG-INFO/SOURCES.txt
eggs/p01.cgi-0.6.1-py3.10.egg/EGG-INFO/dependency_links.txt
eggs/p01.cgi-0.6.1-py3.10.egg/EGG-INFO/namespace_packages.txt
eggs/p01.cgi-0.6.1-py3.10.egg/EGG-INFO/requires.txt
eggs/p01.cgi-0.6.1-py3.10.egg/EGG-INFO/top_level.txt
eggs/p01.cgi-0.6.1-py3.10.egg/p01/cgi/README.txt
eggs/p01.cgi-0.6.1-py3.10.egg/p01/cgi/README_PY2.txt
eggs/p01.cgi-0.6.1-py3.10.egg/p01/cgi/data/large_file.txt
eggs/p01.cgi-0.6.1-py3.10.egg/p01/cgi/data/multipart.txt
eggs/p01.cgi-0.6.1-py3.10.egg/p01/cgi/data/multipart_long.txt
eggs/p01.cgi-0.6.1-py3.10.egg/p01/cgi/data/test.txt
eggs/p01.cgi-0.6.1-py3.10.egg/p01/cgi/data/urlencoded.txt
eggs/p01.cgi-0.6.2-py3.10.egg/EGG-INFO/SOURCES.txt
eggs/p01.cgi-0.6.2-py3.10.egg/EGG-INFO/dependency_links.txt
eggs/p01.cgi-0.6.2-py3.10.egg/EGG-INFO/namespace_packages.txt
eggs/p01.cgi-0.6.2-py3.10.egg/EGG-INFO/requires.txt
eggs/p01.cgi-0.6.2-py3.10.egg/EGG-INFO/top_level.txt
eggs/p01.cgi-0.6.2-py3.10.egg/p01/cgi/README.txt
eggs/p01.cgi-0.6.2-py3.10.egg/p01/cgi/data/large_file.txt
eggs/p01.cgi-0.6.2-py3.10.egg/p01/cgi/data/multipart.txt
eggs/p01.cgi-0.6.2-py3.10.egg/p01/cgi/data/multipart_long.txt
eggs/p01.cgi-0.6.2-py3.10.egg/p01/cgi/data/test.txt
eggs/p01.cgi-0.6.2-py3.10.egg/p01/cgi/data/urlencoded.txt
eggs/p01.checker-0.5.12-py3.10.egg/EGG-INFO/SOURCES.txt
eggs/p01.checker-0.5.12-py3.10.egg/EGG-INFO/dependency_links.txt
eggs/p01.checker-0.5.12-py3.10.egg/EGG-INFO/namespace_packages.txt
eggs/p01.checker-0.5.12-py3.10.egg/EGG-INFO/requires.txt
eggs/p01.checker-0.5.12-py3.10.egg/EGG-INFO/top_level.txt
eggs/p01.checker-0.5.12-py3.10.egg/p01/checker/checker.txt
eggs/p01.checker-0.5.12-py3.10.egg/p01/checker/sample/tab.txt
eggs/p01.checker-0.5.13-py3.10.egg/EGG-INFO/SOURCES.txt
eggs/p01.checker-0.5.13-py3.10.egg/EGG-INFO/dependency_links.txt
eggs/p01.checker-0.5.13-py3.10.egg/EGG-INFO/namespace_packages.txt
eggs/p01.checker-0.5.13-py3.10.egg/EGG-INFO/requires.txt
eggs/p01.checker-0.5.13-py3.10.egg/EGG-INFO/top_level.txt
eggs/p01.checker-0.5.13-py3.10.egg/p01/checker/checker.txt
eggs/p01.checker-0.5.13-py3.10.egg/p01/checker/sample/tab.txt
eggs/p01.json-0.7.2-py3.10.egg/EGG-INFO/SOURCES.txt
eggs/p01.json-0.7.2-py3.10.egg/EGG-INFO/dependency_links.txt
eggs/p01.json-0.7.2-py3.10.egg/EGG-INFO/namespace_packages.txt
eggs/p01.json-0.7.2-py3.10.egg/EGG-INFO/requires.txt
eggs/p01.json-0.7.2-py3.10.egg/EGG-INFO/top_level.txt
eggs/p01.json-0.7.2-py3.10.egg/p01/json/README.txt
eggs/p01.jsonrpc-0.8.0-py3.10.egg/EGG-INFO/SOURCES.txt
eggs/p01.jsonrpc-0.8.0-py3.10.egg/EGG-INFO/dependency_links.txt
eggs/p01.jsonrpc-0.8.0-py3.10.egg/EGG-INFO/namespace_packages.txt
eggs/p01.jsonrpc-0.8.0-py3.10.egg/EGG-INFO/requires.txt
eggs/p01.jsonrpc-0.8.0-py3.10.egg/EGG-INFO/top_level.txt
eggs/p01.jsonrpc-0.8.0-py3.10.egg/p01/jsonrpc/README.txt
eggs/p01.jsonrpc-0.8.0-py3.10.egg/p01/jsonrpc/zcml.txt
eggs/p01.jsonrpc-0.8.1-py3.10.egg/EGG-INFO/SOURCES.txt
eggs/p01.jsonrpc-0.8.1-py3.10.egg/EGG-INFO/dependency_links.txt
eggs/p01.jsonrpc-0.8.1-py3.10.egg/EGG-INFO/namespace_packages.txt
eggs/p01.jsonrpc-0.8.1-py3.10.egg/EGG-INFO/requires.txt
eggs/p01.jsonrpc-0.8.1-py3.10.egg/EGG-INFO/top_level.txt
eggs/p01.jsonrpc-0.8.1-py3.10.egg/p01/jsonrpc/README.txt
eggs/p01.jsonrpc-0.8.1-py3.10.egg/p01/jsonrpc/zcml.txt
eggs/p01.recipe.setup-0.8.19-py3.10.egg/EGG-INFO/SOURCES.txt
eggs/p01.recipe.setup-0.8.19-py3.10.egg/EGG-INFO/dependency_links.txt
